oramask.py
oramask-0.2.3.dist-info/LICENSE
oramask-0.2.3.dist-info/METADATA
oramask-0.2.3.dist-info/WHEEL
oramask-0.2.3.dist-info/top_level.txt
oramask-0.2.3.dist-info/RECORD
