Metadata-Version: 2.1
Name: oramask
Version: 0.2.3
Summary: A simple converter from Oracle date/time masks to strftime format
Home-page: https://github.com/andzhi4/oramask
Author: Viacheslav Andzhich
Author-email: va.public@protonmail.com
License: MIT
Classifier: License :: OSI Approved :: MIT License
Classifier: Programming Language :: Python :: 3
Classifier: Programming Language :: Python :: 3 :: Only
Classifier: Programming Language :: Python :: Implementation :: CPython
Classifier: Programming Language :: Python :: Implementation :: PyPy
Requires-Python: >=3.8
License-File: LICENSE
